tsh/__init__.py
tsh/command.py
tsh/consts.py
tsh/contexts.py
tsh/decorators.py
tsh/errors.py
tsh/process.py
tsh/shell.py
tsh/types.py
tsh-0.0.1.dist-info/LICENSE
tsh-0.0.1.dist-info/METADATA
tsh-0.0.1.dist-info/WHEEL
tsh-0.0.1.dist-info/top_level.txt
tsh-0.0.1.dist-info/RECORD
