Metadata-Version: 2.1
Name: tsh
Version: 0.0.1
Summary: tea-shell - execute command line tools like python functions, while you sit back and sip on your tea.
Home-page: https://github.com/alefnula/tsh
Author: Viktor Kerkez
Author-email: alefnula@gmail.com
Maintainer: Viktor Kerkez
Maintainer-email: alefnula@gmail.com
License: Apache-2.0
Platform: Windows
Platform: POSIX
Platform: MacOSX
Classifier: Programming Language :: Python :: 3
Classifier: Programming Language :: Python :: 3.7
Classifier: License :: OSI Approved :: Apache Software License
Classifier: Operating System :: OS Independent
